Workbook

Sheet KPI_Dashboard
A1: E-COMMERCE SALES PERFORMANCE — KPI DASHBOARD
A2: Prototype dataset: 25 orders | Jan 2026
A4: Total Revenue | B4: =SUMPRODUCT((Raw_Data!T2:T26=1)*Raw_Data!K2:K26*Raw_Data!L2:L26*(1-Raw_Data!M2:M26)) -> 95477.75 | D4: Average Order Value | E4: =B4/SUM(Raw_Data!T2:T26) -> 3978.2396
A6: Total Profit | B6: =SUMPRODUCT((Raw_Data!T2:T26=1)*(Raw_Data!K2:K26*Raw_Data!L2:L26*(1-Raw_Data!M2:M26)-Raw_Data!N2:N26)) -> 23877.75 | D6: Profit Margin % | E6: =B6/B4 -> 0.25008706
A8: Total Orders | B8: =COUNTA(Raw_Data!A2:A26) -> 25 | D8: Conversion Rate % | E8: =SUM(Raw_Data!T2:T26)/25 -> 0.96
A10: Total Customers | B10: =SUMPRODUCT(1/COUNTIF(Raw_Data!D2:D26,Raw_Data!D2:D26)) -> 25 | D10: Return Rate % | E10: =COUNTIF(Raw_Data!V2:V26,"Yes")/SUM(Raw_Data!T2:T26) -> 0.083333333

Sheet Raw_Data
A1: Order_ID | B1: Order_Date | C1: Order_Time | D1: Customer_ID | E1: Gender | F1: Age | G1: City | H1: Region | I1: Product_Name | J1: Category | K1: Quantity | L1: Unit_Price | M1: Discount | N1: Cost | O1: Payment_Method | P1: Order_Status | Q1: Customer_Type | R1: Session_Duration | S1: Pages_Viewed | T1: Order_Completed | U1: Shipping_Days | V1: Return_Status
A2: ORD1001 | B2: 2026-01-03 | C2: 10:15 | D2: CU001 | E2: Male | F2: 24 | G2: Chennai | H2: South | I2: Wireless Mouse | J2: Electronics | K2: 2 | L2: 799 | M2: 0.05 | N2: 1100 | O2: UPI | P2: Delivered | Q2: New | R2: 8.5 | S2: 6 | T2: 1 | U2: 3 | V2: No
A3: ORD1002 | B3: 2026-01-04 | C3: 14:20 | D3: CU002 | E3: Female | F3: 29 | G3: Bangalore | H3: South | I3: Running Shoes | J3: Fashion | K3: 1 | L3: 2499 | M3: 0.1 | N3: 1500 | O3: Card | P3: Delivered | Q3: Returning | R3: 12.2 | S3: 9 | T3: 1 | U3: 4 | V3: No
A4: ORD1003 | B4: 2026-01-05 | C4: 19:45 | D4: CU003 | E4: Male | F4: 34 | G4: Hyderabad | H4: South | I4: Smart Watch | J4: Electronics | K4: 1 | L4: 3999 | M4: 0.08 | N4: 2700 | O4: UPI | P4: Delivered | Q4: New | R4: 15.4 | S4: 11 | T4: 1 | U4: 3 | V4: No
A5: ORD1004 | B5: 2026-01-06 | C5: 21:10 | D5: CU004 | E5: Female | F5: 26 | G5: Mumbai | H5: West | I5: Backpack | J5: Fashion | K5: 2 | L5: 1499 | M5: 0.15 | N5: 1800 | O5: Card | P5: Delivered | Q5: Returning | R5: 9.8 | S5: 7 | T5: 1 | U5: 5 | V5: Yes
A6: ORD1005 | B6: 2026-01-07 | C6: 11:30 | D6: CU005 | E6: Male | F6: 41 | G6: Delhi | H6: North | I6: Office Chair | J6: Furniture | K6: 1 | L6: 6999 | M6: 0.05 | N6: 5200 | O6: Net Banking | P6: Delivered | Q6: Returning | R6: 18.1 | S6: 13 | T6: 1 | U6: 6 | V6: No
A7: ORD1006 | B7: 2026-01-08 | C7: 16:05 | D7: CU006 | E7: Female | F7: 23 | G7: Coimbatore | H7: South | I7: Bluetooth Speaker | J7: Electronics | K7: 2 | L7: 1299 | M7: 0.12 | N7: 1500 | O7: UPI | P7: Delivered | Q7: New | R7: 7.4 | S7: 5 | T7: 1 | U7: 3 | V7: No
A8: ORD1007 | B8: 2026-01-09 | C8: 20:35 | D8: CU007 | E8: Male | F8: 31 | G8: Pune | H8: West | I8: Jeans | J8: Fashion | K8: 3 | L8: 1899 | M8: 0.1 | N8: 3600 | O8: Card | P8: Delivered | Q8: Returning | R8: 11.6 | S8: 8 | T8: 1 | U8: 4 | V8: No
A9: ORD1008 | B9: 2026-01-10 | C9: 09:50 | D9: CU008 | E9: Female | F9: 37 | G9: Kochi | H9: South | I9: Coffee Maker | J9: Home Appliances | K9: 1 | L9: 3299 | M9: 0.07 | N9: 2300 | O9: UPI | P9: Delivered | Q9: New | R9: 14.3 | S9: 10 | T9: 1 | U9: 3 | V9: No
A10: ORD1009 | B10: 2026-01-11 | C10: 18:25 | D10: CU009 | E10: Male | F10: 28 | G10: Kolkata | H10: East | I10: Keyboard | J10: Electronics | K10: 1 | L10: 1799 | M10: 0.05 | N10: 1200 | O10: Card | P10: Cancelled | Q10: New | R10: 6.2 | S10: 4 | T10: 0 | U10: 0 | V10: No
A11: ORD1010 | B11: 2026-01-12 | C11: 22:15 | D11: CU010 | E11: Female | F11: 32 | G11: Chennai | H11: South | I11: Handbag | J11: Fashion | K11: 1 | L11: 2799 | M11: 0.12 | N11: 1700 | O11: UPI | P11: Delivered | Q11: Returning | R11: 13.7 | S11: 9 | T11: 1 | U11: 4 | V11: No
A12: ORD1011 | B12: 2026-01-13 | C12: 13:40 | D12: CU011 | E12: Male | F12: 45 | G12: Delhi | H12: North | I12: Monitor | J12: Electronics | K12: 1 | L12: 8999 | M12: 0.08 | N12: 6900 | O12: Card | P12: Delivered | Q12: Returning | R12: 21.5 | S12: 15 | T12: 1 | U12: 5 | V12: No
A13: ORD1012 | B13: 2026-01-14 | C13: 17:55 | D13: CU012 | E13: Female | F13: 27 | G13: Bangalore | H13: South | I13: Yoga Mat | J13: Sports | K13: 2 | L13: 899 | M13: 0.05 | N13: 1000 | O13: UPI | P13: Delivered | Q13: New | R13: 8.1 | S13: 6 | T13: 1 | U13: 3 | V13: No
... A26: ORD1025 | B26: 2026-01-27 | C26: 14:45 | D26: CU025 | E26: Male | F26: 38 | G26: Pune | H26: West | I26: Laptop Stand | J26: Electronics | K26: 2 | L26: 1999 | M26: 0.08 | N26: 2400 | O26: UPI | P26: Delivered | Q26: New | R26: 11.3 | S26: 8 | T26: 1 | U26: 3 | V26: No

Sheet Data_Quality
A1: DATA QUALITY CHECKS
A3: Check | B3: Result | C3: Formula Used
A4: Total rows | B4: =COUNTA(Raw_Data!A2:A26) -> 25 | C4: COUNTA
A5: Duplicate Order_IDs | B5: =SUMPRODUCT((COUNTIF(Raw_Data!A2:A26,Raw_Data!A2:A26)>1)*1) -> 0 | C5: SUMPRODUCT + COUNTIF
A6: Missing values (any column, row-count) | B6: =SUMPRODUCT(--(COUNTBLANK(Raw_Data!A2:U26)>0)) -> 0 | C6: SUMPRODUCT + COUNTBLANK (row-wise not directly supported; see note)
A7: Missing Order_ID cells | B7: =COUNTBLANK(Raw_Data!A2:A26) -> 0 | C7: COUNTBLANK
A8: Missing Customer_ID cells | B8: =COUNTBLANK(Raw_Data!D2:D26) -> 0 | C8: COUNTBLANK
A9: Negative or zero Unit_Price | B9: =COUNTIF(Raw_Data!L2:L26,"<=0") -> 0 | C9: COUNTIF
A10: Discount out of range (>0.5) | B10: =COUNTIF(Raw_Data!M2:M26,">0.5") -> 0 | C10: COUNTIF
A11: Duplicate full rows (Order_ID basis) | B11: =SUMPRODUCT((COUNTIF(Raw_Data!A2:A26,Raw_Data!A2:A26)>1)*1)/2 -> 0 | C11: Duplicate pair count
A14: Conclusion:
A15: Prototype dataset (25 rows) contains 0 duplicate Order_IDs and 0 missing critical fields (Order_ID, Customer_ID, Unit_Price). Data is clean and ready for analysis.

Sheet Calculated_Fields
A1: Order_ID | B1: Order_Date | C1: Order_Hour | D1: Customer_ID | E1: Customer_Segment | F1: Category (via lookup) | G1: Revenue | H1: Discount_Amount | I1: Cost | J1: Profit | K1: Profit_Margin_%
A2: =Raw_Data!A2 -> ORD1001 | B2: =Raw_Data!B2 -> 2026-01-03 | C2: =VALUE(LEFT(Raw_Data!C2,FIND(":",Raw_Data!C2)-1)) -> 10 | D2: =Raw_Data!D2 -> CU001 | E2: =_xlfn.IFS(Raw_Data!Q2="New","New Customer",Raw_Data!Q2="Returning","Returning Customer",TRUE(),"Unclassified") -> New Customer | F2: =INDEX(Raw_Data!J:J,MATCH(A2,Raw_Data!A:A,0)) -> Electronics | G2: =Raw_Data!K2*Raw_Data!L2*(1-Raw_Data!M2) -> 1518.1 | H2: =Raw_Data!K2*Raw_Data!L2*Raw_Data!M2 -> 79.9 | I2: =Raw_Data!N2 -> 1100 | J2: =G2-I2 -> 418.1 | K2: =IFERROR(J2/G2,0) -> 0.27541005
A3: =Raw_Data!A3 -> ORD1002 | B3: =Raw_Data!B3 -> 2026-01-04 | C3: =VALUE(LEFT(Raw_Data!C3,FIND(":",Raw_Data!C3)-1)) -> 14 | D3: =Raw_Data!D3 -> CU002 | E3: =_xlfn.IFS(Raw_Data!Q3="New","New Customer",Raw_Data!Q3="Returning","Returning Customer",TRUE(),"Unclassified") -> Returning Customer | F3: =INDEX(Raw_Data!J:J,MATCH(A3,Raw_Data!A:A,0)) -> Fashion | G3: =Raw_Data!K3*Raw_Data!L3*(1-Raw_Data!M3) -> 2249.1 | H3: =Raw_Data!K3*Raw_Data!L3*Raw_Data!M3 -> 249.9 | I3: =Raw_Data!N3 -> 1500 | J3: =G3-I3 -> 749.1 | K3: =IFERROR(J3/G3,0) -> 0.33306656
A4: =Raw_Data!A4 -> ORD1003 | B4: =Raw_Data!B4 -> 2026-01-05 | C4: =VALUE(LEFT(Raw_Data!C4,FIND(":",Raw_Data!C4)-1)) -> 19 | D4: =Raw_Data!D4 -> CU003 | E4: =_xlfn.IFS(Raw_Data!Q4="New","New Customer",Raw_Data!Q4="Returning","Returning Customer",TRUE(),"Unclassified") -> New Customer | F4: =INDEX(Raw_Data!J:J,MATCH(A4,Raw_Data!A:A,0)) -> Electronics | G4: =Raw_Data!K4*Raw_Data!L4*(1-Raw_Data!M4) -> 3679.08 | H4: =Raw_Data!K4*Raw_Data!L4*Raw_Data!M4 -> 319.92 | I4: =Raw_Data!N4 -> 2700 | J4: =G4-I4 -> 979.08 | K4: =IFERROR(J4/G4,0) -> 0.26612088
A5: =Raw_Data!A5 -> ORD1004 | B5: =Raw_Data!B5 -> 2026-01-06 | C5: =VALUE(LEFT(Raw_Data!C5,FIND(":",Raw_Data!C5)-1)) -> 21 | D5: =Raw_Data!D5 -> CU004 | E5: =_xlfn.IFS(Raw_Data!Q5="New","New Customer",Raw_Data!Q5="Returning","Returning Customer",TRUE(),"Unclassified") -> Returning Customer | F5: =INDEX(Raw_Data!J:J,MATCH(A5,Raw_Data!A:A,0)) -> Fashion | G5: =Raw_Data!K5*Raw_Data!L5*(1-Raw_Data!M5) -> 2548.3 | H5: =Raw_Data!K5*Raw_Data!L5*Raw_Data!M5 -> 449.7 | I5: =Raw_Data!N5 -> 1800 | J5: =G5-I5 -> 748.3 | K5: =IFERROR(J5/G5,0) -> 0.29364674
A6: =Raw_Data!A6 -> ORD1005 | B6: =Raw_Data!B6 -> 2026-01-07 | C6: =VALUE(LEFT(Raw_Data!C6,FIND(":",Raw_Data!C6)-1)) -> 11 | D6: =Raw_Data!D6 -> CU005 | E6: =_xlfn.IFS(Raw_Data!Q6="New","New Customer",Raw_Data!Q6="Returning","Returning Customer",TRUE(),"Unclassified") -> Returning Customer | F6: =INDEX(Raw_Data!J:J,MATCH(A6,Raw_Data!A:A,0)) -> Furniture | G6: =Raw_Data!K6*Raw_Data!L6*(1-Raw_Data!M6) -> 6649.05 | H6: =Raw_Data!K6*Raw_Data!L6*Raw_Data!M6 -> 349.95 | I6: =Raw_Data!N6 -> 5200 | J6: =G6-I6 -> 1449.05 | K6: =IFERROR(J6/G6,0) -> 0.21793339
A7: =Raw_Data!A7 -> ORD1006 | B7: =Raw_Data!B7 -> 2026-01-08 | C7: =VALUE(LEFT(Raw_Data!C7,FIND(":",Raw_Data!C7)-1)) -> 16 | D7: =Raw_Data!D7 -> CU006 | E7: =_xlfn.IFS(Raw_Data!Q7="New","New Customer",Raw_Data!Q7="Returning","Returning Customer",TRUE(),"Unclassified") -> New Customer | F7: =INDEX(Raw_Data!J:J,MATCH(A7,Raw_Data!A:A,0)) -> Electronics | G7: =Raw_Data!K7*Raw_Data!L7*(1-Raw_Data!M7) -> 2286.24 | H7: =Raw_Data!K7*Raw_Data!L7*Raw_Data!M7 -> 311.76 | I7: =Raw_Data!N7 -> 1500 | J7: =G7-I7 -> 786.24 | K7: =IFERROR(J7/G7,0) -> 0.3439009
A8: =Raw_Data!A8 -> ORD1007 | B8: =Raw_Data!B8 -> 2026-01-09 | C8: =VALUE(LEFT(Raw_Data!C8,FIND(":",Raw_Data!C8)-1)) -> 20 | D8: =Raw_Data!D8 -> CU007 | E8: =_xlfn.IFS(Raw_Data!Q8="New","New Customer",Raw_Data!Q8="Returning","Returning Customer",TRUE(),"Unclassified") -> Returning Customer | F8: =INDEX(Raw_Data!J:J,MATCH(A8,Raw_Data!A:A,0)) -> Fashion | G8: =Raw_Data!K8*Raw_Data!L8*(1-Raw_Data!M8) -> 5127.3 | H8: =Raw_Data!K8*Raw_Data!L8*Raw_Data!M8 -> 569.7 | I8: =Raw_Data!N8 -> 3600 | J8: =G8-I8 -> 1527.3 | K8: =IFERROR(J8/G8,0) -> 0.29787608
A9: =Raw_Data!A9 -> ORD1008 | B9: =Raw_Data!B9 -> 2026-01-10 | C9: =VALUE(LEFT(Raw_Data!C9,FIND(":",Raw_Data!C9)-1)) -> 9 | D9: =Raw_Data!D9 -> CU008 | E9: =_xlfn.IFS(Raw_Data!Q9="New","New Customer",Raw_Data!Q9="Returning","Returning Customer",TRUE(),"Unclassified") -> New Customer | F9: =INDEX(Raw_Data!J:J,MATCH(A9,Raw_Data!A:A,0)) -> Home Appliances | G9: =Raw_Data!K9*Raw_Data!L9*(1-Raw_Data!M9) -> 3068.07 | H9: =Raw_Data!K9*Raw_Data!L9*Raw_Data!M9 -> 230.93 | I9: =Raw_Data!N9 -> 2300 | J9: =G9-I9 -> 768.07 | K9: =IFERROR(J9/G9,0) -> 0.25034305
A10: =Raw_Data!A10 -> ORD1009 | B10: =Raw_Data!B10 -> 2026-01-11 | C10: =VALUE(LEFT(Raw_Data!C10,FIND(":",Raw_Data!C10)-1)) -> 18 | D10: =Raw_Data!D10 -> CU009 | E10: =_xlfn.IFS(Raw_Data!Q10="New","New Customer",Raw_Data!Q10="Returning","Returning Customer",TRUE(),"Unclassified") -> New Customer | F10: =INDEX(Raw_Data!J:J,MATCH(A10,Raw_Data!A:A,0)) -> Electronics | G10: =Raw_Data!K10*Raw_Data!L10*(1-Raw_Data!M10) -> 1709.05 | H10: =Raw_Data!K10*Raw_Data!L10*Raw_Data!M10 -> 89.95 | I10: =Raw_Data!N10 -> 1200 | J10: =G10-I10 -> 509.05 | K10: =IFERROR(J10/G10,0) -> 0.29785553
A11: =Raw_Data!A11 -> ORD1010 | B11: =Raw_Data!B11 -> 2026-01-12 | C11: =VALUE(LEFT(Raw_Data!C11,FIND(":",Raw_Data!C11)-1)) -> 22 | D11: =Raw_Data!D11 -> CU010 | E11: =_xlfn.IFS(Raw_Data!Q11="New","New Customer",Raw_Data!Q11="Returning","Returning Customer",TRUE(),"Unclassified") -> Returning Customer | F11: =INDEX(Raw_Data!J:J,MATCH(A11,Raw_Data!A:A,0)) -> Fashion | G11: =Raw_Data!K11*Raw_Data!L11*(1-Raw_Data!M11) -> 2463.12 | H11: =Raw_Data!K11*Raw_Data!L11*Raw_Data!M11 -> 335.88 | I11: =Raw_Data!N11 -> 1700 | J11: =G11-I11 -> 763.12 | K11: =IFERROR(J11/G11,0) -> 0.30981844
A12: =Raw_Data!A12 -> ORD1011 | B12: =Raw_Data!B12 -> 2026-01-13 | C12: =VALUE(LEFT(Raw_Data!C12,FIND(":",Raw_Data!C12)-1)) -> 13 | D12: =Raw_Data!D12 -> CU011 | E12: =_xlfn.IFS(Raw_Data!Q12="New","New Customer",Raw_Data!Q12="Returning","Returning Customer",TRUE(),"Unclassified") -> Returning Customer | F12: =INDEX(Raw_Data!J:J,MATCH(A12,Raw_Data!A:A,0)) -> Electronics | G12: =Raw_Data!K12*Raw_Data!L12*(1-Raw_Data!M12) -> 8279.08 | H12: =Raw_Data!K12*Raw_Data!L12*Raw_Data!M12 -> 719.92 | I12: =Raw_Data!N12 -> 6900 | J12: =G12-I12 -> 1379.08 | K12: =IFERROR(J12/G12,0) -> 0.16657406
A13: =Raw_Data!A13 -> ORD1012 | B13: =Raw_Data!B13 -> 2026-01-14 | C13: =VALUE(LEFT(Raw_Data!C13,FIND(":",Raw_Data!C13)-1)) -> 17 | D13: =Raw_Data!D13 -> CU012 | E13: =_xlfn.IFS(Raw_Data!Q13="New","New Customer",Raw_Data!Q13="Returning","Returning Customer",TRUE(),"Unclassified") -> New Customer | F13: =INDEX(Raw_Data!J:J,MATCH(A13,Raw_Data!A:A,0)) -> Sports | G13: =Raw_Data!K13*Raw_Data!L13*(1-Raw_Data!M13) -> 1708.1 | H13: =Raw_Data!K13*Raw_Data!L13*Raw_Data!M13 -> 89.9 | I13: =Raw_Data!N13 -> 1000 | J13: =G13-I13 -> 708.1 | K13: =IFERROR(J13/G13,0) -> 0.41455418
... A26: =Raw_Data!A26 -> ORD1025 | B26: =Raw_Data!B26 -> 2026-01-27 | C26: =VALUE(LEFT(Raw_Data!C26,FIND(":",Raw_Data!C26)-1)) -> 14 | D26: =Raw_Data!D26 -> CU025 | E26: =_xlfn.IFS(Raw_Data!Q26="New","New Customer",Raw_Data!Q26="Returning","Returning Customer",TRUE(),"Unclassified") -> New Customer | F26: =INDEX(Raw_Data!J:J,MATCH(A26,Raw_Data!A:A,0)) -> Electronics | G26: =Raw_Data!K26*Raw_Data!L26*(1-Raw_Data!M26) -> 3678.16 | H26: =Raw_Data!K26*Raw_Data!L26*Raw_Data!M26 -> 319.84 | I26: =Raw_Data!N26 -> 2400 | J26: =G26-I26 -> 1278.16 | K26: =IFERROR(J26/G26,0) -> 0.34749984
A28: Note: Excel's newer XLOOKUP() is used conceptually as the lookup approach (=XLOOKUP(A2,Raw_Data!Order_ID,Raw_Data!Category)); this workbook implements the same result with INDEX/MATCH for maximum compatibility across Excel versions.

Sheet Pivot_Summary
A1: PIVOT-STYLE SUMMARY (SUMIFS / COUNTIFS)
A2: Tip: Select Raw_Data range and Insert > PivotTable in Excel for a native, drag-and-drop pivot.
A4: Revenue & Orders by Category
A5: Category | B5: Orders | C5: Revenue
A6: Books | B6: =COUNTIF(Raw_Data!J2:J26,A6) -> 1 | C6: =SUMPRODUCT((Raw_Data!J2:J26=$A6)*Raw_Data!K2:K26*Raw_Data!L2:L26*(1-Raw_Data!M2:M26)) -> 2370.25
A7: Electronics | B7: =COUNTIF(Raw_Data!J2:J26,A7) -> 10 | C7: =SUMPRODUCT((Raw_Data!J2:J26=$A7)*Raw_Data!K2:K26*Raw_Data!L2:L26*(1-Raw_Data!M2:M26)) -> 45558.22
A8: Fashion | B8: =COUNTIF(Raw_Data!J2:J26,A8) -> 7 | C8: =SUMPRODUCT((Raw_Data!J2:J26=$A8)*Raw_Data!K2:K26*Raw_Data!L2:L26*(1-Raw_Data!M2:M26)) -> 21733.74
A9: Furniture | B9: =COUNTIF(Raw_Data!J2:J26,A9) -> 1 | C9: =SUMPRODUCT((Raw_Data!J2:J26=$A9)*Raw_Data!K2:K26*Raw_Data!L2:L26*(1-Raw_Data!M2:M26)) -> 6649.05
A10: Home Appliances | B10: =COUNTIF(Raw_Data!J2:J26,A10) -> 5 | C10: =SUMPRODUCT((Raw_Data!J2:J26=$A10)*Raw_Data!K2:K26*Raw_Data!L2:L26*(1-Raw_Data!M2:M26)) -> 19167.44
A11: Sports | B11: =COUNTIF(Raw_Data!J2:J26,A11) -> 1 | C11: =SUMPRODUCT((Raw_Data!J2:J26=$A11)*Raw_Data!K2:K26*Raw_Data!L2:L26*(1-Raw_Data!M2:M26)) -> 1708.1
A14: Revenue & Orders by Region
A15: Region | B15: Orders | C15: Revenue
A16: East | B16: =COUNTIF(Raw_Data!H2:H26,A16) -> 2 | C16: =SUMPRODUCT((Raw_Data!H2:H26=$A16)*Raw_Data!K2:K26*Raw_Data!L2:L26*(1-Raw_Data!M2:M26)) -> 4468.13
A17: North | B17: =COUNTIF(Raw_Data!H2:H26,A17) -> 3 | C17: =SUMPRODUCT((Raw_Data!H2:H26=$A17)*Raw_Data!K2:K26*Raw_Data!L2:L26*(1-Raw_Data!M2:M26)) -> 17298.38
A18: South | B18: =COUNTIF(Raw_Data!H2:H26,A18) -> 14 | C18: =SUMPRODUCT((Raw_Data!H2:H26=$A18)*Raw_Data!K2:K26*Raw_Data!L2:L26*(1-Raw_Data!M2:M26)) -> 54151.73
A19: West | B19: =COUNTIF(Raw_Data!H2:H26,A19) -> 6 | C19: =SUMPRODUCT((Raw_Data!H2:H26=$A19)*Raw_Data!K2:K26*Raw_Data!L2:L26*(1-Raw_Data!M2:M26)) -> 21268.56
A22: New vs Returning Customers
A23: Customer_Type | B23: Orders | C23: Revenue
A24: New | B24: =COUNTIF(Raw_Data!Q2:Q26,A24) -> 12 | C24: =SUMPRODUCT((Raw_Data!Q2:Q26=$A24)*Raw_Data!K2:K26*Raw_Data!L2:L26*(1-Raw_Data!M2:M26)) -> 44076.76
A25: Returning | B25: =COUNTIF(Raw_Data!Q2:Q26,A25) -> 13 | C25: =SUMPRODUCT((Raw_Data!Q2:Q26=$A25)*Raw_Data!K2:K26*Raw_Data!L2:L26*(1-Raw_Data!M2:M26)) -> 53110.04
A28: Orders by Payment Method
A29: Payment_Method | B29: Orders
A30: Card | B30: =COUNTIFS(Raw_Data!O2:O26,A30) -> 11
A31: Net Banking | B31: =COUNTIFS(Raw_Data!O2:O26,A31) -> 2
A32: UPI | B32: =COUNTIFS(Raw_Data!O2:O26,A32) -> 12
